[
  {
    "full_name": "girliemac/a-picture-is-worth-a-1000-words",
    "stargazers_count": 9773,
    "open_issues_count": 11,
    "forks_count": 650
  },
  {
    "full_name": "CryptozombiesHQ/cryptozombies-lesson-code",
    "stargazers_count": 1793,
    "open_issues_count": 24,
    "forks_count": 795
  },
  {
    "full_name": "terryum/awesome-deep-learning-papers",
    "stargazers_count": 23997,
    "open_issues_count": 34,
    "forks_count": 4480
  },
  {
    "full_name": "pharmapsychotic/clip-interrogator",
    "stargazers_count": 213,
    "open_issues_count": 1,
    "forks_count": 37
  },
  {
    "full_name": "CompVis/stable-diffusion",
    "stargazers_count": 24656,
    "open_issues_count": 228,
    "forks_count": 3847
  },
  {
    "full_name": "man-c/pycoingecko",
    "stargazers_count": 892,
    "open_issues_count": 13,
    "forks_count": 228
  },
  {
    "full_name": "sappkevin/leetcode",
    "stargazers_count": 1,
    "open_issues_count": 0,
    "forks_count": 0
  },
  {
    "full_name": "neetcode-gh/leetcode",
    "stargazers_count": 1862,
    "open_issues_count": 71,
    "forks_count": 986
  }
]